docassemble.ALWeaver-1.11.0-py3.10-nspkg.pth
docassemble/ALWeaver/__init__.py
docassemble/ALWeaver/advertise_capabilities.py
docassemble/ALWeaver/custom_values.py
docassemble/ALWeaver/draggable_table.py
docassemble/ALWeaver/generator_constants.py
docassemble/ALWeaver/interview_generator.py
docassemble/ALWeaver/list_taxonomy.py
docassemble/ALWeaver/requirements.txt
docassemble/ALWeaver/test_docx_files.py
docassemble/ALWeaver/test_feeling_lucky.py
docassemble/ALWeaver/test_fill_in_field_attributes.py
docassemble/ALWeaver/test_map_names.py
docassemble/ALWeaver/test_pdf_files.py
docassemble/ALWeaver/validate_template_files.py
docassemble/ALWeaver/data/questions/assembly_line.yml
docassemble/ALWeaver/data/questions/config.yml
docassemble/ALWeaver/data/questions/feedback.yml
docassemble/ALWeaver/data/questions/generator-test.yml
docassemble/ALWeaver/data/questions/review_screen.yml
docassemble/ALWeaver/data/questions/template_validation.yml
docassemble/ALWeaver/data/questions/test_next_steps_document.yml
docassemble/ALWeaver/data/questions/visual.yml
docassemble/ALWeaver/data/questions/weaver_configuration.yml
docassemble/ALWeaver/data/sources/README.md
docassemble/ALWeaver/data/sources/configuration_capabilities.yml
docassemble/ALWeaver/data/sources/list-taxonomy.csv
docassemble/ALWeaver/data/sources/test_1.feature
docassemble/ALWeaver/data/sources/test_civil_docketing_statement.pdf
docassemble/ALWeaver/data/static/README.md
docassemble/ALWeaver/data/static/branding_extra.png
docassemble/ALWeaver/data/static/drag.png
docassemble/ALWeaver/data/static/draggable_table.css
docassemble/ALWeaver/data/static/draggable_table.js
docassemble/ALWeaver/data/static/example_question_layout.png
docassemble/ALWeaver/data/static/green_light.png
docassemble/ALWeaver/data/static/logo.png
docassemble/ALWeaver/data/static/logo.svg
docassemble/ALWeaver/data/static/next_steps_appeal.docx
docassemble/ALWeaver/data/static/next_steps_existing_case.docx
docassemble.ALWeaver-1.11.0.dist-info/LICENSE.md
docassemble.ALWeaver-1.11.0.dist-info/METADATA
docassemble.ALWeaver-1.11.0.dist-info/WHEEL
docassemble.ALWeaver-1.11.0.dist-info/namespace_packages.txt
docassemble.ALWeaver-1.11.0.dist-info/top_level.txt
docassemble.ALWeaver-1.11.0.dist-info/RECORD
