Metadata-Version: 2.1
Name: docassemble.ALWeaver
Version: 1.11.0
Home-page: https://docassemble.org
Author: Quinten Steenhuis
Author-email: qsteenhuis@suffolk.edu
License: MIT
License-File: LICENSE.md
Requires-Dist: PyYAML >=5.1.2
Requires-Dist: beautifulsoup4 >=4.11.1
Requires-Dist: docassemble.ALToolbox >=0.4.2
Requires-Dist: docassemble.AssemblyLine >=2.11.3
Requires-Dist: docx2python >=1.27.1
Requires-Dist: more-itertools >=8.6.0
Requires-Dist: numpy >=1.0.4
Requires-Dist: pikepdf >=5.1.1
Requires-Dist: scikit-learn >=0.0
Requires-Dist: spacy >=3.2.0
Requires-Dist: formfyxer >=0.3.0a1
